{
  "orgUnit": "y1Zt8YWUdNN",
  "reports": {
        "Children ARV Regimen 2nd Line": {
                "dataValues":[
                        {
                        "categoryOptionCombo": "mPQoKHoKpE3",
                        "dataElement": "ctVH46atted",
                        "row": 1,
                        "column": 2
                        },
						{
                        "categoryOptionCombo": "mPQoKHoKpE3",
                        "dataElement": "fdjlhYvIo52",
                        "row": 2,
                        "column": 2
                        },
						{
                        "categoryOptionCombo": "mPQoKHoKpE3",
                        "dataElement": "nA5APc3cXah",
                        "row": 3,
                        "column": 2
                        },
						{
                        "categoryOptionCombo": "mPQoKHoKpE3",
                        "dataElement": "pRImanAxgJV",
                        "row": 4,
                        "column": 2
                        },
						{
                        "categoryOptionCombo": "mPQoKHoKpE3",
                        "dataElement": "H9U8sgvzpD4",
                        "row": 5,
                        "column": 2
                        },
						{
                        "categoryOptionCombo": "mPQoKHoKpE3",
                        "dataElement": "pJcDO1c9x1M",
                        "row": 6,
                        "column": 2
                        },
						{
                        "categoryOptionCombo": "mPQoKHoKpE3",
                        "dataElement": "se8ne49VPcx",
                        "row": 7,
                        "column": 2
                        },
						{
                        "categoryOptionCombo": "mPQoKHoKpE3",
                        "dataElement": "bkmHNKG5PfT",
                        "row": 8,
                        "column": 2
                        },
						{
                        "categoryOptionCombo": "mPQoKHoKpE3",
                        "dataElement": "BKqLvcHF7jF",
                        "row": 9,
                        "column": 2
                        },
						
						
						
						{
                        "categoryOptionCombo": "Nu3y8NRbmmf",
                        "dataElement": "ctVH46atted",
                        "row": 1,
                        "column": 3
                        },
						{
                        "categoryOptionCombo": "Nu3y8NRbmmf",
                        "dataElement": "fdjlhYvIo52",
                        "row": 2,
                        "column": 3
                        },
						{
                        "categoryOptionCombo": "Nu3y8NRbmmf",
                        "dataElement": "nA5APc3cXah",
                        "row": 3,
                        "column": 3
                        },
						{
                        "categoryOptionCombo": "Nu3y8NRbmmf",
                        "dataElement": "pRImanAxgJV",
                        "row": 4,
                        "column": 3
                        },
						{
                        "categoryOptionCombo": "Nu3y8NRbmmf",
                        "dataElement": "H9U8sgvzpD4",
                        "row": 5,
                        "column": 3
                        },
						{
                        "categoryOptionCombo": "Nu3y8NRbmmf",
                        "dataElement": "pJcDO1c9x1M",
                        "row": 6,
                        "column": 3
                        },
						{
                        "categoryOptionCombo": "Nu3y8NRbmmf",
                        "dataElement": "se8ne49VPcx",
                        "row": 7,
                        "column": 3
                        },
						{
                        "categoryOptionCombo": "Nu3y8NRbmmf",
                        "dataElement": "bkmHNKG5PfT",
                        "row": 8,
                        "column": 3
                        },
						{
                        "categoryOptionCombo": "Nu3y8NRbmmf",
                        "dataElement": "BKqLvcHF7jF",
                        "row": 9,
                        "column": 3
                        },
						
						
						{
                        "categoryOptionCombo": "TWJNKrVCaa9",
                        "dataElement": "ctVH46atted",
                        "row": 1,
                        "column": 4
                        },
						{
                        "categoryOptionCombo": "TWJNKrVCaa9",
                        "dataElement": "fdjlhYvIo52",
                        "row": 2,
                        "column": 4
                        },
						{
                        "categoryOptionCombo": "TWJNKrVCaa9",
                        "dataElement": "nA5APc3cXah",
                        "row": 3,
                        "column": 4
                        },
						{
                        "categoryOptionCombo": "TWJNKrVCaa9",
                        "dataElement": "pRImanAxgJV",
                        "row": 4,
                        "column": 4
                        },
						{
                        "categoryOptionCombo": "TWJNKrVCaa9",
                        "dataElement": "H9U8sgvzpD4",
                        "row": 5,
                        "column": 4
                        },
						{
                        "categoryOptionCombo": "TWJNKrVCaa9",
                        "dataElement": "pJcDO1c9x1M",
                        "row": 6,
                        "column": 4
                        },
						{
                        "categoryOptionCombo": "TWJNKrVCaa9",
                        "dataElement": "se8ne49VPcx",
                        "row": 7,
                        "column": 4
                        },
						{
                        "categoryOptionCombo": "TWJNKrVCaa9",
                        "dataElement": "bkmHNKG5PfT",
                        "row": 8,
                        "column": 4
                        },
						{
                        "categoryOptionCombo": "TWJNKrVCaa9",
                        "dataElement": "BKqLvcHF7jF",
                        "row": 9,
                        "column": 4
                        },
						
						
						{
                        "categoryOptionCombo": "SF1ah36chuk",
                        "dataElement": "ctVH46atted",
                        "row": 1,
                        "column": 5
                        },
						{
                        "categoryOptionCombo": "SF1ah36chuk",
                        "dataElement": "fdjlhYvIo52",
                        "row": 2,
                        "column": 5
                        },
						{
                        "categoryOptionCombo": "SF1ah36chuk",
                        "dataElement": "nA5APc3cXah",
                        "row": 3,
                        "column": 5
                        },
						{
                        "categoryOptionCombo": "SF1ah36chuk",
                        "dataElement": "pRImanAxgJV",
                        "row": 4,
                        "column": 5
                        },
						{
                        "categoryOptionCombo": "SF1ah36chuk",
                        "dataElement": "H9U8sgvzpD4",
                        "row": 5,
                        "column": 5
                        },
						{
                        "categoryOptionCombo": "SF1ah36chuk",
                        "dataElement": "pJcDO1c9x1M",
                        "row": 6,
                        "column": 5
                        },
						{
                        "categoryOptionCombo": "SF1ah36chuk",
                        "dataElement": "se8ne49VPcx",
                        "row": 7,
                        "column": 5
                        },
						{
                        "categoryOptionCombo": "SF1ah36chuk",
                        "dataElement": "bkmHNKG5PfT",
                        "row": 8,
                        "column": 5
                        },
						{
                        "categoryOptionCombo": "SF1ah36chuk",
                        "dataElement": "BKqLvcHF7jF",
                        "row": 9,
                        "column": 5
                        },
						
						
						{
                        "categoryOptionCombo": "mxrT6vEtJof",
                        "dataElement": "ctVH46atted",
                        "row": 1,
                        "column": 6
                        },
						{
                        "categoryOptionCombo": "mxrT6vEtJof",
                        "dataElement": "fdjlhYvIo52",
                        "row": 2,
                        "column": 6
                        },
						{
                        "categoryOptionCombo": "mxrT6vEtJof",
                        "dataElement": "nA5APc3cXah",
                        "row": 3,
                        "column": 6
                        },
						{
                        "categoryOptionCombo": "mxrT6vEtJof",
                        "dataElement": "pRImanAxgJV",
                        "row": 4,
                        "column": 6
                        },
						{
                        "categoryOptionCombo": "mxrT6vEtJof",
                        "dataElement": "H9U8sgvzpD4",
                        "row": 5,
                        "column": 6
                        },
						{
                        "categoryOptionCombo": "mxrT6vEtJof",
                        "dataElement": "pJcDO1c9x1M",
                        "row": 6,
                        "column": 6
                        },
						{
                        "categoryOptionCombo": "mxrT6vEtJof",
                        "dataElement": "se8ne49VPcx",
                        "row": 7,
                        "column": 6
                        },
						{
                        "categoryOptionCombo": "mxrT6vEtJof",
                        "dataElement": "bkmHNKG5PfT",
                        "row": 8,
                        "column": 6
                        },
						{
                        "categoryOptionCombo": "mxrT6vEtJof",
                        "dataElement": "BKqLvcHF7jF",
                        "row": 9,
                        "column": 6
                        },
						
						
						{
                        "categoryOptionCombo": "Y9mjCBlX0qM",
                        "dataElement": "ctVH46atted",
                        "row": 1,
                        "column": 7
                        },
						{
                        "categoryOptionCombo": "Y9mjCBlX0qM",
                        "dataElement": "fdjlhYvIo52",
                        "row": 2,
                        "column": 7
                        },
						{
                        "categoryOptionCombo": "Y9mjCBlX0qM",
                        "dataElement": "nA5APc3cXah",
                        "row": 3,
                        "column": 7
                        },
						{
                        "categoryOptionCombo": "Y9mjCBlX0qM",
                        "dataElement": "pRImanAxgJV",
                        "row": 4,
                        "column": 7
                        },
						{
                        "categoryOptionCombo": "Y9mjCBlX0qM",
                        "dataElement": "H9U8sgvzpD4",
                        "row": 5,
                        "column": 7
                        },
						{
                        "categoryOptionCombo": "Y9mjCBlX0qM",
                        "dataElement": "pJcDO1c9x1M",
                        "row": 6,
                        "column": 7
                        },
						{
                        "categoryOptionCombo": "Y9mjCBlX0qM",
                        "dataElement": "se8ne49VPcx",
                        "row": 7,
                        "column": 7
                        },
						{
                        "categoryOptionCombo": "Y9mjCBlX0qM",
                        "dataElement": "bkmHNKG5PfT",
                        "row": 8,
                        "column": 7
                        },
						{
                        "categoryOptionCombo": "Y9mjCBlX0qM",
                        "dataElement": "BKqLvcHF7jF",
                        "row": 9,
                        "column": 7
                        },
						
						
						{
                        "categoryOptionCombo": "uT3QLbThgHo",
                        "dataElement": "ctVH46atted",
                        "row": 1,
                        "column": 8
                        },
						{
                        "categoryOptionCombo": "uT3QLbThgHo",
                        "dataElement": "fdjlhYvIo52",
                        "row": 2,
                        "column": 8
                        },
						{
                        "categoryOptionCombo": "uT3QLbThgHo",
                        "dataElement": "nA5APc3cXah",
                        "row": 3,
                        "column": 8
                        },
						{
                        "categoryOptionCombo": "uT3QLbThgHo",
                        "dataElement": "pRImanAxgJV",
                        "row": 4,
                        "column": 8
                        },
						{
                        "categoryOptionCombo": "uT3QLbThgHo",
                        "dataElement": "H9U8sgvzpD4",
                        "row": 5,
                        "column": 8
                        },
						{
                        "categoryOptionCombo": "uT3QLbThgHo",
                        "dataElement": "pJcDO1c9x1M",
                        "row": 6,
                        "column": 8
                        },
						{
                        "categoryOptionCombo": "uT3QLbThgHo",
                        "dataElement": "se8ne49VPcx",
                        "row": 7,
                        "column": 8
                        },
						{
                        "categoryOptionCombo": "uT3QLbThgHo",
                        "dataElement": "bkmHNKG5PfT",
                        "row": 8,
                        "column": 8
                        },
						{
                        "categoryOptionCombo": "uT3QLbThgHo",
                        "dataElement": "BKqLvcHF7jF",
                        "row": 9,
                        "column": 8
                        },
						
						
						{
                        "categoryOptionCombo": "J2nTJY1kBOe",
                        "dataElement": "ctVH46atted",
                        "row": 1,
                        "column": 9
                        },
						{
                        "categoryOptionCombo": "J2nTJY1kBOe",
                        "dataElement": "fdjlhYvIo52",
                        "row": 2,
                        "column": 9
                        },
						{
                        "categoryOptionCombo": "J2nTJY1kBOe",
                        "dataElement": "nA5APc3cXah",
                        "row": 3,
                        "column": 9
                        },
						{
                        "categoryOptionCombo": "J2nTJY1kBOe",
                        "dataElement": "pRImanAxgJV",
                        "row": 4,
                        "column": 9
                        },
						{
                        "categoryOptionCombo": "J2nTJY1kBOe",
                        "dataElement": "H9U8sgvzpD4",
                        "row": 5,
                        "column": 9
                        },
						{
                        "categoryOptionCombo": "J2nTJY1kBOe",
                        "dataElement": "pJcDO1c9x1M",
                        "row": 6,
                        "column": 9
                        },
						{
                        "categoryOptionCombo": "J2nTJY1kBOe",
                        "dataElement": "se8ne49VPcx",
                        "row": 7,
                        "column": 9
                        },
						{
                        "categoryOptionCombo": "J2nTJY1kBOe",
                        "dataElement": "bkmHNKG5PfT",
                        "row": 8,
                        "column": 9
                        },
						{
                        "categoryOptionCombo": "J2nTJY1kBOe",
                        "dataElement": "BKqLvcHF7jF",
                        "row": 9,
                        "column": 9
                        }
                ]
        }
  }
}
